cupy/__init__.py
cupy/_environment.py
cupy/_util.cp310-win_amd64.pyd
cupy/_version.py
cupy/cublas.py
cupy/cudnn.cp310-win_amd64.pyd
cupy/cusolver.cp310-win_amd64.pyd
cupy/cusparse.py
cupy/cutensor.cp310-win_amd64.pyd
cupy/.data/_wheel.json
cupy/.data/lib/nvToolsExt64_1.dll
cupy/_binary/__init__.py
cupy/_binary/elementwise.py
cupy/_binary/packing.py
cupy/_core/__init__.py
cupy/_core/_accelerator.cp310-win_amd64.pyd
cupy/_core/_carray.cp310-win_amd64.pyd
cupy/_core/_codeblock.py
cupy/_core/_cub_reduction.cp310-win_amd64.pyd
cupy/_core/_dtype.cp310-win_amd64.pyd
cupy/_core/_fusion_interface.py
cupy/_core/_fusion_kernel.cp310-win_amd64.pyd
cupy/_core/_fusion_op.py
cupy/_core/_fusion_optimization.py
cupy/_core/_fusion_thread_local.cp310-win_amd64.pyd
cupy/_core/_fusion_trace.cp310-win_amd64.pyd
cupy/_core/_fusion_variable.cp310-win_amd64.pyd
cupy/_core/_gufuncs.py
cupy/_core/_kernel.cp310-win_amd64.pyd
cupy/_core/_memory_range.cp310-win_amd64.pyd
cupy/_core/_optimize_config.cp310-win_amd64.pyd
cupy/_core/_reduction.cp310-win_amd64.pyd
cupy/_core/_routines_binary.cp310-win_amd64.pyd
cupy/_core/_routines_indexing.cp310-win_amd64.pyd
cupy/_core/_routines_linalg.cp310-win_amd64.pyd
cupy/_core/_routines_logic.cp310-win_amd64.pyd
cupy/_core/_routines_manipulation.cp310-win_amd64.pyd
cupy/_core/_routines_math.cp310-win_amd64.pyd
cupy/_core/_routines_sorting.cp310-win_amd64.pyd
cupy/_core/_routines_statistics.cp310-win_amd64.pyd
cupy/_core/_scalar.cp310-win_amd64.pyd
cupy/_core/_ufuncs.py
cupy/_core/core.cp310-win_amd64.pyd
cupy/_core/dlpack.cp310-win_amd64.pyd
cupy/_core/flags.cp310-win_amd64.pyd
cupy/_core/fusion.cp310-win_amd64.pyd
cupy/_core/internal.cp310-win_amd64.pyd
cupy/_core/new_fusion.cp310-win_amd64.pyd
cupy/_core/raw.cp310-win_amd64.pyd
cupy/_core/syncdetect.py
cupy/_core/include/cupy/README.md
cupy/_core/include/cupy/atomics.cuh
cupy/_core/include/cupy/carray.cuh
cupy/_core/include/cupy/complex.cuh
cupy/_core/include/cupy/cuComplex_bridge.h
cupy_cuda117-10.6.0.dist-info/METADATA
cupy_cuda117-10.6.0.dist-info/WHEEL
cupy_cuda117-10.6.0.dist-info/license.rst
cupy_cuda117-10.6.0.dist-info/top_level.txt
cupy_cuda117-10.6.0.dist-info/RECORD
